COPYRIGHT.txt
LICENSE.txt
README.txt
buildout.cfg
setup.py
src/zc/__init__.py
src/zc.recipe.rhrc.egg-info/PKG-INFO
src/zc.recipe.rhrc.egg-info/SOURCES.txt
src/zc.recipe.rhrc.egg-info/dependency_links.txt
src/zc.recipe.rhrc.egg-info/entry_points.txt
src/zc.recipe.rhrc.egg-info/namespace_packages.txt
src/zc.recipe.rhrc.egg-info/not-zip-safe
src/zc.recipe.rhrc.egg-info/requires.txt
src/zc.recipe.rhrc.egg-info/top_level.txt
src/zc/recipe/__init__.py
src/zc/recipe/rhrc/README.txt
src/zc/recipe/rhrc/__init__.py
src/zc/recipe/rhrc/tests.py