Metadata-Version: 1.0
Name: zc.recipe.rhrc
Version: 1.4.0
Summary: ZC Buildout recipe for Redhat RC scripts
Home-page: UNKNOWN
Author: Jim Fulton
Author-email: jim@zope.com
License: ZPL 2.1
Keywords: buildout
Platform: UNKNOWN
